{
  "project_info": {
    "project_number": "117765314222",
    "firebase_url": "https://flashbotany.firebaseio.com",
    "project_id": "flashbotany",
    "storage_bucket": "flashbotany.appspot.com"
  },
  "client": [
    {
      "client_info": {
        "mobilesdk_app_id": "1:117765314222:android:3bca55e09a0670abad3f3f",
        "android_client_info": {
          "package_name": "com.jlbennett.flashbotany"
        }
      },
      "oauth_client": [
        {
          "client_id": "117765314222-05f4t9u2h712bdt2e4g1mrp9up9kvpq0.apps.googleusercontent.com",
          "client_type": 3
        }
      ],
      "api_key": [
        {
          "current_key": "AIzaSyByS8Bo75s63ny8ZeEWwwF1NCKjeOU88_0"
        }
      ],
      "services": {
        "appinvite_service": {
          "other_platform_oauth_client": [
            {
              "client_id": "117765314222-05f4t9u2h712bdt2e4g1mrp9up9kvpq0.apps.googleusercontent.com",
              "client_type": 3
            }
          ]
        }
      }
    }
  ],
  "configuration_version": "1"
}